compysition
tests
