Metadata-Version: 1.1
Name: compysition
Version: 1.2.53
Summary: Build event pipeline servers with minimal effort.
Home-page: https://github.com/fiebiga/compysition
Author: Adam Fiebig
Author-email: fiebig.adam@gmail.com
License: UNKNOWN
Download-URL: https://github.com/fiebiga/compysition/tarball/master
Platform: Linux
Classifier: Development Status :: 5 - Production/Stable
Classifier: License :: OSI Approved :: GNU General Public License v3 or later (GPLv3+)
Classifier: Programming Language :: Python
Classifier: Programming Language :: Python :: 2
Classifier: Programming Language :: Python :: 2.7
Classifier: Programming Language :: Python :: 3.3
Classifier: Programming Language :: Python :: Implementation :: PyPy
Classifier: Intended Audience :: Developers
Classifier: Intended Audience :: System Administrators
